mwtp/__init__.py
mwtp/_alias_record.py
mwtp/_namespace_data.py
mwtp/_namespace_id_map.py
mwtp/_php_to_upper_map.py
mwtp/_title_like.py
mwtp/exceptions.py
mwtp/namespace.py
mwtp/parser.py
mwtp/py.typed
mwtp/title.py
mwtp-4.0.0.dist-info/LICENSE
mwtp-4.0.0.dist-info/METADATA
mwtp-4.0.0.dist-info/WHEEL
mwtp-4.0.0.dist-info/top_level.txt
mwtp-4.0.0.dist-info/RECORD
