Metadata-Version: 2.1
Name: mwtp
Version: 4.0.0
Summary: A parser for MediaWiki titles
Author-email: NDKDD <adhominem259@gmail.com>
License: GPL-3.0-only
Project-URL: Homepage, https://github.com/NguoiDungKhongDinhDanh/mwtp
Project-URL: Bug tracker, https://github.com/NguoiDungKhongDinhDanh/mwtp/issues
Project-URL: Documentation, https://mwtp.readthedocs.io/
Keywords: mediawiki,title,pagename,parser
Classifier: Development Status :: 5 - Production/Stable
Classifier: Intended Audience :: Developers
Classifier: Operating System :: Microsoft :: Windows
Classifier: Topic :: Software Development :: Build Tools
Classifier: License :: OSI Approved :: GNU General Public License (GPL)
Classifier: Programming Language :: Python :: 3
Classifier: Programming Language :: Python :: 3.10
Classifier: Programming Language :: Python :: 3.11
Classifier: Programming Language :: Python :: 3.12
Classifier: Programming Language :: Python :: 3 :: Only
Classifier: Typing :: Typed
Requires-Python: >=3.10
License-File: LICENSE
Provides-Extra: build
Requires-Dist: build ~=1.0.3 ; extra == 'build'
Requires-Dist: setuptools ~=67.6.1 ; extra == 'build'
Requires-Dist: twine ~=4.0.2 ; extra == 'build'
Provides-Extra: dev
Requires-Dist: black ~=24.1.1 ; extra == 'dev'
Requires-Dist: mypy ~=1.4.1 ; extra == 'dev'
Provides-Extra: test
Requires-Dist: mypy ~=1.4.1 ; extra == 'test'
Requires-Dist: pytest ~=7.4.0 ; extra == 'test'
Requires-Dist: pytest-cov ~=4.1.0 ; extra == 'test'
Requires-Dist: tox ~=4.6.4 ; extra == 'test'
